noia_sdk/__init__.py
noia_sdk/__main__.py
noia_sdk/api_client.py
noia_sdk/configuration.py
noia_sdk/rest.py
noia_sdk/utils.py
noia_sdk/api/__init__.py
noia_sdk/api/auth_api.py
noia_sdk/api/platform_api.py
noia_sdk/models/__init__.py
noia_sdk/models/admin_agent_config.py
noia_sdk/models/admin_change_password_object.py
noia_sdk/models/agent_connection_object.py
noia_sdk/models/agent_connection_response_connection_performance_array_array_.py
noia_sdk/models/agent_connection_status.py
noia_sdk/models/agent_group_object.py
noia_sdk/models/agent_interface_bw_object.py
noia_sdk/models/agent_interface_object.py
noia_sdk/models/agent_locked_fields.py
noia_sdk/models/agent_message_payload.py
noia_sdk/models/agent_message_type.py
noia_sdk/models/agent_name_id_pair.py
noia_sdk/models/agent_network_object.py
noia_sdk/models/agent_object.py
noia_sdk/models/agent_path_object.py
noia_sdk/models/agent_provider_object.py
noia_sdk/models/agent_service_object.py
noia_sdk/models/agent_service_types.py
noia_sdk/models/agent_services_update_object.py
noia_sdk/models/agent_services_update_object_changes.py
noia_sdk/models/agent_success_response.py
noia_sdk/models/any_of_agent_message_payload.py
noia_sdk/models/any_of_platform_agent_message_payload.py
noia_sdk/models/any_of_platform_agents_hit_object_source_severity.py
noia_sdk/models/any_of_platform_response_error_item_value.py
noia_sdk/models/any_of_settings_types.py
noia_sdk/models/any_of_vpp_callable_object.py
noia_sdk/models/any_of_wg_callable_object.py
noia_sdk/models/any_ofbody_cmd.py
noia_sdk/models/any_ofinline_response204.py
noia_sdk/models/api_key_object.py
noia_sdk/models/app_connect_config_object.py
noia_sdk/models/app_connect_config_object_config.py
noia_sdk/models/app_connect_config_object_config_params.py
noia_sdk/models/app_connect_config_object_metadata.py
noia_sdk/models/app_connect_object.py
noia_sdk/models/app_disconnect_object.py
noia_sdk/models/app_disconnect_to_status_types.py
noia_sdk/models/app_object.py
noia_sdk-0.1.1.dist-info/METADATA
noia_sdk-0.1.1.dist-info/WHEEL
noia_sdk-0.1.1.dist-info/entry_points.txt
noia_sdk-0.1.1.dist-info/top_level.txt
noia_sdk-0.1.1.dist-info/RECORD
