Metadata-Version: 2.1
Name: noia-sdk
Version: 0.1.1
Summary: NOIA Python SDK
Home-page: https://gitlab.com/noianetwork-team/noia-sdk-python/
Author: Andrius Mikonis
Author-email: andrius@noia.network
License: UNKNOWN
Platform: any
Requires-Python: >=3.6
Requires-Dist: certifi (>=14.05.14)
Requires-Dist: six (>=1.10)
Requires-Dist: python-dateutil (>=2.5.3)
Requires-Dist: setuptools (>=21.0.0)
Requires-Dist: urllib3 (>=1.15.1)
Requires-Dist: click (>=7.1.0)
Requires-Dist: prettytable
Requires-Dist: pyyaml
Requires-Dist: dataclasses
